odoo/addons/l10n_es_account_banking_sepa_fsdd/README.rst
odoo/addons/l10n_es_account_banking_sepa_fsdd/__init__.py
odoo/addons/l10n_es_account_banking_sepa_fsdd/__manifest__.py
odoo/addons/l10n_es_account_banking_sepa_fsdd/i18n/ca.po
odoo/addons/l10n_es_account_banking_sepa_fsdd/i18n/es.po
odoo/addons/l10n_es_account_banking_sepa_fsdd/i18n/es_ES.po
odoo/addons/l10n_es_account_banking_sepa_fsdd/i18n/fr.po
odoo/addons/l10n_es_account_banking_sepa_fsdd/i18n/l10n_es_account_banking_sepa_fsdd.pot
odoo/addons/l10n_es_account_banking_sepa_fsdd/i18n/nl.po
odoo/addons/l10n_es_account_banking_sepa_fsdd/i18n/pt_BR.po
odoo/addons/l10n_es_account_banking_sepa_fsdd/i18n/sl.po
odoo/addons/l10n_es_account_banking_sepa_fsdd/models/__init__.py
odoo/addons/l10n_es_account_banking_sepa_fsdd/models/account_payment_mode.py
odoo/addons/l10n_es_account_banking_sepa_fsdd/models/account_payment_order.py
odoo/addons/l10n_es_account_banking_sepa_fsdd/static/description/icon.png
odoo/addons/l10n_es_account_banking_sepa_fsdd/tests/__init__.py
odoo/addons/l10n_es_account_banking_sepa_fsdd/tests/test_l10n_es_account_banking_sepa_fsdd.py
odoo/addons/l10n_es_account_banking_sepa_fsdd/views/payment_mode_view.xml
odoo11_addon_l10n_es_account_banking_sepa_fsdd-11.0.1.0.1.dist-info/METADATA
odoo11_addon_l10n_es_account_banking_sepa_fsdd-11.0.1.0.1.dist-info/WHEEL
odoo11_addon_l10n_es_account_banking_sepa_fsdd-11.0.1.0.1.dist-info/top_level.txt
odoo11_addon_l10n_es_account_banking_sepa_fsdd-11.0.1.0.1.dist-info/RECORD
